odoo/addons/mail_preview_audio/README.rst
odoo/addons/mail_preview_audio/__init__.py
odoo/addons/mail_preview_audio/__manifest__.py
odoo/addons/mail_preview_audio/i18n/mail_preview_audio.pot
odoo/addons/mail_preview_audio/readme/CONTRIBUTORS.rst
odoo/addons/mail_preview_audio/readme/DESCRIPTION.rst
odoo/addons/mail_preview_audio/static/description/icon.png
odoo/addons/mail_preview_audio/static/description/index.html
odoo/addons/mail_preview_audio/static/src/js/preview.esm.js
odoo/addons/mail_preview_audio/static/src/xml/preview.xml
odoo_addon_mail_preview_audio-15.0.1.0.0.3.dist-info/METADATA
odoo_addon_mail_preview_audio-15.0.1.0.0.3.dist-info/WHEEL
odoo_addon_mail_preview_audio-15.0.1.0.0.3.dist-info/top_level.txt
odoo_addon_mail_preview_audio-15.0.1.0.0.3.dist-info/RECORD
